genereg/DataMatrices.py
genereg/FeatureSelection.py
genereg/GeneExpression.py
genereg/GenesMapping.py
genereg/Initialize.py
genereg/LinearRegression.py
genereg/Methylation.py
genereg/RegulatoryGenes.py
genereg/SummaryResults.py
genereg/TranscriptionFactors.py
genereg/__init__.py
genereg-0.1.1.dist-info/METADATA
genereg-0.1.1.dist-info/RECORD
genereg-0.1.1.dist-info/WHEEL
genereg-0.1.1.dist-info/top_level.txt
