Metadata-Version: 2.1
Name: genereg
Version: 0.1.1
Summary: A library for analyzing the regulation systems of target genes belonging to genomic pathways relevant for a specific cancer type.
Home-page: https://github.com/Kia23/genereg
Author: Kia23
Author-email: kia34.r18.dev@gmail.com
License: UNKNOWN
Platform: UNKNOWN
Classifier: Programming Language :: Python :: 3
Classifier: License :: OSI Approved :: Apache Software License
Classifier: Operating System :: Microsoft :: Windows
Classifier: Topic :: Scientific/Engineering :: Bio-Informatics
Requires-Dist: gmql
Requires-Dist: pandas
Requires-Dist: numpy
Requires-Dist: openpyxl
Requires-Dist: math
Requires-Dist: pickle
Requires-Dist: xlsxwriter
Requires-Dist: collections
Requires-Dist: sklearn
Requires-Dist: statsmodels
Requires-Dist: os
Requires-Dist: urllib
Requires-Dist: mlxtend
